<?xml version="1.0" encoding="utf-8"?>
<ufinterface receiver="K01" sender="mes" roottag="" replace="Y" isexchange="Y" groupcode="" filename="" billtype="46" account="001">
  <bill id="">
    <billhead>
      <cgeneralhid>
      </cgeneralhid>
      <pk_group>001</pk_group>
      <corpoid>K01</corpoid>
      <corpvid>K01</corpvid>
      <vbillcode>
      </vbillcode>
      <dbilldate>2016/11/27 0:00:00</dbilldate>
      <pk_org>K01</pk_org>
      <pk_org_v>K01</pk_org_v>
      <cgeneralbid>
        <item>
          <cgeneralbid>
          </cgeneralbid>
          <crowno>1</crowno>
          <pk_group>001</pk_group>
          <corpoid>K01</corpoid>
          <corpvid>K01</corpvid>
          <cstateid>2</cstateid>
          <cmaterialoid>1202020013</cmaterialoid>
          <cmaterialvid>1202020013</cmaterialvid>
          <vfree1>265</vfree1>
          <vfree2>01</vfree2>
          <vfree3>01</vfree3>
          <vfree4>
          </vfree4>
          <vfree5>
          </vfree5>
          <vfree6>
          </vfree6>
          <cunitid>Pcs</cunitid>
          <castunitid>WA</castunitid>
          <vchangerate>1/265.0000</vchangerate>
          <vbatchcode>161111020700</vbatchcode>
          <nshouldnum>30</nshouldnum>
          <nshouldassistnum>7950.000</nshouldassistnum>
          <nnum>30</nnum>
          <nassistnum>7950.000</nassistnum>
          <dbizdate>2016-11-28 07:50:00</dbizdate>
          <vproductbatch>1MO-16110002</vproductbatch>
          <csourcebillhid>1001A11000000017VHPQ</csourcebillhid>
          <csourcebillbid>1001A11000000017VHQ2</csourcebillbid>
          <csourcetype>55A4</csourcetype>
          <csourcetranstype>0001A110000000001MSI</csourcetranstype>
          <csourcebillbid>1001A11000000017VHQ2</csourcebillbid>
          <vsourcebillcode>1BG-16111123</vsourcebillcode>
          <vsourcerowno>1001A11000000017VHPS</vsourcerowno>
          <cprojectid>
          </cprojectid>
          <casscustid>
          </casscustid>
          <cfirsttype>55C2</cfirsttype>
          <cfirsttranstype>0001A110000000001MSJ</cfirsttranstype>
          <cfirstbillhid>1001A11000000016JXCR</cfirstbillhid>
          <vfirstbillcode>1MO-16110002</vfirstbillcode>
          <vfirstrowno>
          </vfirstrowno>
          <cfirstbillbid>1001A11000000016JXCR</cfirstbillbid>
          <vnotebody>
          </vnotebody>
          <bbarcodeclose>N</bbarcodeclose>
          <bonroadflag>N</bonroadflag>
          <dproducedate>2016/11/27 0:00:00</dproducedate>
          <pk_org>K01</pk_org>
          <pk_org_v>K01</pk_org_v>
          <cbodywarehouseid>CP002</cbodywarehouseid>
          <flargess>N</flargess>
          <pk_batchcode>
          </pk_batchcode>
          <csrcmaterialoid>
          </csrcmaterialoid>
          <csrcmaterialvid>
          </csrcmaterialvid>
          <cproductid>1202020013</cproductid>
          <fproductclass>1</fproductclass>
          <vbdef1>8086.080000</vbdef1>
        </item>
        <item>
          <cgeneralbid>
          </cgeneralbid>
          <crowno>2</crowno>
          <pk_group>001</pk_group>
          <corpoid>K01</corpoid>
          <corpvid>K01</corpvid>
          <cstateid>2</cstateid>
          <cmaterialoid>1202020013</cmaterialoid>
          <cmaterialvid>1202020013</cmaterialvid>
          <vfree1>265</vfree1>
          <vfree2>01</vfree2>
          <vfree3>01</vfree3>
          <vfree4>
          </vfree4>
          <vfree5>
          </vfree5>
          <vfree6>
          </vfree6>
          <cunitid>Pcs</cunitid>
          <castunitid>WA</castunitid>
          <vchangerate>1/265.0000</vchangerate>
          <vbatchcode>161111020706</vbatchcode>
          <nshouldnum>30</nshouldnum>
          <nshouldassistnum>7950.000</nshouldassistnum>
          <nnum>30</nnum>
          <nassistnum>7950.000</nassistnum>
          <dbizdate>2016-11-28 07:50:00</dbizdate>
          <vproductbatch>1MO-16110002</vproductbatch>
          <csourcebillhid>1001A11000000017VHPQ</csourcebillhid>
          <csourcebillbid>1001A11000000017VHQ3</csourcebillbid>
          <csourcetype>55A4</csourcetype>
          <csourcetranstype>0001A110000000001MSI</csourcetranstype>
          <csourcebillbid>1001A11000000017VHQ3</csourcebillbid>
          <vsourcebillcode>1BG-16111123</vsourcebillcode>
          <vsourcerowno>1001A11000000017VHPT</vsourcerowno>
          <cprojectid>
          </cprojectid>
          <casscustid>
          </casscustid>
          <cfirsttype>55C2</cfirsttype>
          <cfirsttranstype>0001A110000000001MSJ</cfirsttranstype>
          <cfirstbillhid>1001A11000000016JXCR</cfirstbillhid>
          <vfirstbillcode>1MO-16110002</vfirstbillcode>
          <vfirstrowno>
          </vfirstrowno>
          <cfirstbillbid>1001A11000000016JXCR</cfirstbillbid>
          <vnotebody>
          </vnotebody>
          <bbarcodeclose>N</bbarcodeclose>
          <bonroadflag>N</bonroadflag>
          <dproducedate>2016/11/27 0:00:00</dproducedate>
          <pk_org>K01</pk_org>
          <pk_org_v>K01</pk_org_v>
          <cbodywarehouseid>CP002</cbodywarehouseid>
          <flargess>N</flargess>
          <pk_batchcode>
          </pk_batchcode>
          <csrcmaterialoid>
          </csrcmaterialoid>
          <csrcmaterialvid>
          </csrcmaterialvid>
          <cproductid>1202020013</cproductid>
          <fproductclass>1</fproductclass>
          <vbdef1>8086.790000</vbdef1>
        </item>
        <item>
          <cgeneralbid>
          </cgeneralbid>
          <crowno>3</crowno>
          <pk_group>001</pk_group>
          <corpoid>K01</corpoid>
          <corpvid>K01</corpvid>
          <cstateid>2</cstateid>
          <cmaterialoid>1202020013</cmaterialoid>
          <cmaterialvid>1202020013</cmaterialvid>
          <vfree1>265</vfree1>
          <vfree2>01</vfree2>
          <vfree3>01</vfree3>
          <vfree4>
          </vfree4>
          <vfree5>
          </vfree5>
          <vfree6>
          </vfree6>
          <cunitid>Pcs</cunitid>
          <castunitid>WA</castunitid>
          <vchangerate>1/265.0000</vchangerate>
          <vbatchcode>161111020708</vbatchcode>
          <nshouldnum>30</nshouldnum>
          <nshouldassistnum>7950.000</nshouldassistnum>
          <nnum>30</nnum>
          <nassistnum>7950.000</nassistnum>
          <dbizdate>2016-11-28 07:50:00</dbizdate>
          <vproductbatch>1MO-16110002</vproductbatch>
          <csourcebillhid>1001A11000000017VHPQ</csourcebillhid>
          <csourcebillbid>1001A11000000017VHQ4</csourcebillbid>
          <csourcetype>55A4</csourcetype>
          <csourcetranstype>0001A110000000001MSI</csourcetranstype>
          <csourcebillbid>1001A11000000017VHQ4</csourcebillbid>
          <vsourcebillcode>1BG-16111123</vsourcebillcode>
          <vsourcerowno>1001A11000000017VHPU</vsourcerowno>
          <cprojectid>
          </cprojectid>
          <casscustid>
          </casscustid>
          <cfirsttype>55C2</cfirsttype>
          <cfirsttranstype>0001A110000000001MSJ</cfirsttranstype>
          <cfirstbillhid>1001A11000000016JXCR</cfirstbillhid>
          <vfirstbillcode>1MO-16110002</vfirstbillcode>
          <vfirstrowno>
          </vfirstrowno>
          <cfirstbillbid>1001A11000000016JXCR</cfirstbillbid>
          <vnotebody>
          </vnotebody>
          <bbarcodeclose>N</bbarcodeclose>
          <bonroadflag>N</bonroadflag>
          <dproducedate>2016/11/27 0:00:00</dproducedate>
          <pk_org>K01</pk_org>
          <pk_org_v>K01</pk_org_v>
          <cbodywarehouseid>CP002</cbodywarehouseid>
          <flargess>N</flargess>
          <pk_batchcode>
          </pk_batchcode>
          <csrcmaterialoid>
          </csrcmaterialoid>
          <csrcmaterialvid>
          </csrcmaterialvid>
          <cproductid>1202020013</cproductid>
          <fproductclass>1</fproductclass>
          <vbdef1>8084.070000</vbdef1>
        </item>
        <item>
          <cgeneralbid>
          </cgeneralbid>
          <crowno>4</crowno>
          <pk_group>001</pk_group>
          <corpoid>K01</corpoid>
          <corpvid>K01</corpvid>
          <cstateid>2</cstateid>
          <cmaterialoid>1202020013</cmaterialoid>
          <cmaterialvid>1202020013</cmaterialvid>
          <vfree1>265</vfree1>
          <vfree2>01</vfree2>
          <vfree3>01</vfree3>
          <vfree4>
          </vfree4>
          <vfree5>
          </vfree5>
          <vfree6>
          </vfree6>
          <cunitid>Pcs</cunitid>
          <castunitid>WA</castunitid>
          <vchangerate>1/265.0000</vchangerate>
          <vbatchcode>161111020709</vbatchcode>
          <nshouldnum>30</nshouldnum>
          <nshouldassistnum>7950.000</nshouldassistnum>
          <nnum>30</nnum>
          <nassistnum>7950.000</nassistnum>
          <dbizdate>2016-11-28 07:50:00</dbizdate>
          <vproductbatch>1MO-16110002</vproductbatch>
          <csourcebillhid>1001A11000000017VHPQ</csourcebillhid>
          <csourcebillbid>1001A11000000017VHQ5</csourcebillbid>
          <csourcetype>55A4</csourcetype>
          <csourcetranstype>0001A110000000001MSI</csourcetranstype>
          <csourcebillbid>1001A11000000017VHQ5</csourcebillbid>
          <vsourcebillcode>1BG-16111123</vsourcebillcode>
          <vsourcerowno>1001A11000000017VHPV</vsourcerowno>
          <cprojectid>
          </cprojectid>
          <casscustid>
          </casscustid>
          <cfirsttype>55C2</cfirsttype>
          <cfirsttranstype>0001A110000000001MSJ</cfirsttranstype>
          <cfirstbillhid>1001A11000000016JXCR</cfirstbillhid>
          <vfirstbillcode>1MO-16110002</vfirstbillcode>
          <vfirstrowno>
          </vfirstrowno>
          <cfirstbillbid>1001A11000000016JXCR</cfirstbillbid>
          <vnotebody>
          </vnotebody>
          <bbarcodeclose>N</bbarcodeclose>
          <bonroadflag>N</bonroadflag>
          <dproducedate>2016/11/27 0:00:00</dproducedate>
          <pk_org>K01</pk_org>
          <pk_org_v>K01</pk_org_v>
          <cbodywarehouseid>CP002</cbodywarehouseid>
          <flargess>N</flargess>
          <pk_batchcode>
          </pk_batchcode>
          <csrcmaterialoid>
          </csrcmaterialoid>
          <csrcmaterialvid>
          </csrcmaterialvid>
          <cproductid>1202020013</cproductid>
          <fproductclass>1</fproductclass>
          <vbdef1>8082.140000</vbdef1>
        </item>
        <item>
          <cgeneralbid>
          </cgeneralbid>
          <crowno>5</crowno>
          <pk_group>001</pk_group>
          <corpoid>K01</corpoid>
          <corpvid>K01</corpvid>
          <cstateid>2</cstateid>
          <cmaterialoid>1202020013</cmaterialoid>
          <cmaterialvid>1202020013</cmaterialvid>
          <vfree1>265</vfree1>
          <vfree2>01</vfree2>
          <vfree3>01</vfree3>
          <vfree4>
          </vfree4>
          <vfree5>
          </vfree5>
          <vfree6>
          </vfree6>
          <cunitid>Pcs</cunitid>
          <castunitid>WA</castunitid>
          <vchangerate>1/265.0000</vchangerate>
          <vbatchcode>161111020712</vbatchcode>
          <nshouldnum>30</nshouldnum>
          <nshouldassistnum>7950.000</nshouldassistnum>
          <nnum>30</nnum>
          <nassistnum>7950.000</nassistnum>
          <dbizdate>2016-11-28 07:50:00</dbizdate>
          <vproductbatch>1MO-16110002</vproductbatch>
          <csourcebillhid>1001A11000000017VHPQ</csourcebillhid>
          <csourcebillbid>1001A11000000017VHQ6</csourcebillbid>
          <csourcetype>55A4</csourcetype>
          <csourcetranstype>0001A110000000001MSI</csourcetranstype>
          <csourcebillbid>1001A11000000017VHQ6</csourcebillbid>
          <vsourcebillcode>1BG-16111123</vsourcebillcode>
          <vsourcerowno>1001A11000000017VHPW</vsourcerowno>
          <cprojectid>
          </cprojectid>
          <casscustid>
          </casscustid>
          <cfirsttype>55C2</cfirsttype>
          <cfirsttranstype>0001A110000000001MSJ</cfirsttranstype>
          <cfirstbillhid>1001A11000000016JXCR</cfirstbillhid>
          <vfirstbillcode>1MO-16110002</vfirstbillcode>
          <vfirstrowno>
          </vfirstrowno>
          <cfirstbillbid>1001A11000000016JXCR</cfirstbillbid>
          <vnotebody>
          </vnotebody>
          <bbarcodeclose>N</bbarcodeclose>
          <bonroadflag>N</bonroadflag>
          <dproducedate>2016/11/27 0:00:00</dproducedate>
          <pk_org>K01</pk_org>
          <pk_org_v>K01</pk_org_v>
          <cbodywarehouseid>CP002</cbodywarehouseid>
          <flargess>N</flargess>
          <pk_batchcode>
          </pk_batchcode>
          <csrcmaterialoid>
          </csrcmaterialoid>
          <csrcmaterialvid>
          </csrcmaterialvid>
          <cproductid>1202020013</cproductid>
          <fproductclass>1</fproductclass>
          <vbdef1>8084.790000</vbdef1>
        </item>
        <item>
          <cgeneralbid>
          </cgeneralbid>
          <crowno>6</crowno>
          <pk_group>001</pk_group>
          <corpoid>K01</corpoid>
          <corpvid>K01</corpvid>
          <cstateid>2</cstateid>
          <cmaterialoid>1202020013</cmaterialoid>
          <cmaterialvid>1202020013</cmaterialvid>
          <vfree1>265</vfree1>
          <vfree2>01</vfree2>
          <vfree3>01</vfree3>
          <vfree4>
          </vfree4>
          <vfree5>
          </vfree5>
          <vfree6>
          </vfree6>
          <cunitid>Pcs</cunitid>
          <castunitid>WA</castunitid>
          <vchangerate>1/265.0000</vchangerate>
          <vbatchcode>161111020714</vbatchcode>
          <nshouldnum>30</nshouldnum>
          <nshouldassistnum>7950.000</nshouldassistnum>
          <nnum>30</nnum>
          <nassistnum>7950.000</nassistnum>
          <dbizdate>2016-11-28 07:50:00</dbizdate>
          <vproductbatch>1MO-16110002</vproductbatch>
          <csourcebillhid>1001A11000000017VHPQ</csourcebillhid>
          <csourcebillbid>1001A11000000017VHQ7</csourcebillbid>
          <csourcetype>55A4</csourcetype>
          <csourcetranstype>0001A110000000001MSI</csourcetranstype>
          <csourcebillbid>1001A11000000017VHQ7</csourcebillbid>
          <vsourcebillcode>1BG-16111123</vsourcebillcode>
          <vsourcerowno>1001A11000000017VHPX</vsourcerowno>
          <cprojectid>
          </cprojectid>
          <casscustid>
          </casscustid>
          <cfirsttype>55C2</cfirsttype>
          <cfirsttranstype>0001A110000000001MSJ</cfirsttranstype>
          <cfirstbillhid>1001A11000000016JXCR</cfirstbillhid>
          <vfirstbillcode>1MO-16110002</vfirstbillcode>
          <vfirstrowno>
          </vfirstrowno>
          <cfirstbillbid>1001A11000000016JXCR</cfirstbillbid>
          <vnotebody>
          </vnotebody>
          <bbarcodeclose>N</bbarcodeclose>
          <bonroadflag>N</bonroadflag>
          <dproducedate>2016/11/27 0:00:00</dproducedate>
          <pk_org>K01</pk_org>
          <pk_org_v>K01</pk_org_v>
          <cbodywarehouseid>CP002</cbodywarehouseid>
          <flargess>N</flargess>
          <pk_batchcode>
          </pk_batchcode>
          <csrcmaterialoid>
          </csrcmaterialoid>
          <csrcmaterialvid>
          </csrcmaterialvid>
          <cproductid>1202020013</cproductid>
          <fproductclass>1</fproductclass>
          <vbdef1>8083.960000</vbdef1>
        </item>
        <item>
          <cgeneralbid>
          </cgeneralbid>
          <crowno>7</crowno>
          <pk_group>001</pk_group>
          <corpoid>K01</corpoid>
          <corpvid>K01</corpvid>
          <cstateid>2</cstateid>
          <cmaterialoid>1202020013</cmaterialoid>
          <cmaterialvid>1202020013</cmaterialvid>
          <vfree1>265</vfree1>
          <vfree2>01</vfree2>
          <vfree3>01</vfree3>
          <vfree4>
          </vfree4>
          <vfree5>
          </vfree5>
          <vfree6>
          </vfree6>
          <cunitid>Pcs</cunitid>
          <castunitid>WA</castunitid>
          <vchangerate>1/265.0000</vchangerate>
          <vbatchcode>161111020715</vbatchcode>
          <nshouldnum>30</nshouldnum>
          <nshouldassistnum>7950.000</nshouldassistnum>
          <nnum>30</nnum>
          <nassistnum>7950.000</nassistnum>
          <dbizdate>2016-11-28 07:50:00</dbizdate>
          <vproductbatch>1MO-16110002</vproductbatch>
          <csourcebillhid>1001A11000000017VHPQ</csourcebillhid>
          <csourcebillbid>1001A11000000017VHQ8</csourcebillbid>
          <csourcetype>55A4</csourcetype>
          <csourcetranstype>0001A110000000001MSI</csourcetranstype>
          <csourcebillbid>1001A11000000017VHQ8</csourcebillbid>
          <vsourcebillcode>1BG-16111123</vsourcebillcode>
          <vsourcerowno>1001A11000000017VHPY</vsourcerowno>
          <cprojectid>
          </cprojectid>
          <casscustid>
          </casscustid>
          <cfirsttype>55C2</cfirsttype>
          <cfirsttranstype>0001A110000000001MSJ</cfirsttranstype>
          <cfirstbillhid>1001A11000000016JXCR</cfirstbillhid>
          <vfirstbillcode>1MO-16110002</vfirstbillcode>
          <vfirstrowno>
          </vfirstrowno>
          <cfirstbillbid>1001A11000000016JXCR</cfirstbillbid>
          <vnotebody>
          </vnotebody>
          <bbarcodeclose>N</bbarcodeclose>
          <bonroadflag>N</bonroadflag>
          <dproducedate>2016/11/27 0:00:00</dproducedate>
          <pk_org>K01</pk_org>
          <pk_org_v>K01</pk_org_v>
          <cbodywarehouseid>CP002</cbodywarehouseid>
          <flargess>N</flargess>
          <pk_batchcode>
          </pk_batchcode>
          <csrcmaterialoid>
          </csrcmaterialoid>
          <csrcmaterialvid>
          </csrcmaterialvid>
          <cproductid>1202020013</cproductid>
          <fproductclass>1</fproductclass>
          <vbdef1>8074.470000</vbdef1>
        </item>
        <item>
          <cgeneralbid>
          </cgeneralbid>
          <crowno>8</crowno>
          <pk_group>001</pk_group>
          <corpoid>K01</corpoid>
          <corpvid>K01</corpvid>
          <cstateid>2</cstateid>
          <cmaterialoid>1202020013</cmaterialoid>
          <cmaterialvid>1202020013</cmaterialvid>
          <vfree1>265</vfree1>
          <vfree2>01</vfree2>
          <vfree3>01</vfree3>
          <vfree4>
          </vfree4>
          <vfree5>
          </vfree5>
          <vfree6>
          </vfree6>
          <cunitid>Pcs</cunitid>
          <castunitid>WA</castunitid>
          <vchangerate>1/265.0000</vchangerate>
          <vbatchcode>161111020716</vbatchcode>
          <nshouldnum>30</nshouldnum>
          <nshouldassistnum>7950.000</nshouldassistnum>
          <nnum>30</nnum>
          <nassistnum>7950.000</nassistnum>
          <dbizdate>2016-11-28 07:50:00</dbizdate>
          <vproductbatch>1MO-16110002</vproductbatch>
          <csourcebillhid>1001A11000000017VHPQ</csourcebillhid>
          <csourcebillbid>1001A11000000017VHQ9</csourcebillbid>
          <csourcetype>55A4</csourcetype>
          <csourcetranstype>0001A110000000001MSI</csourcetranstype>
          <csourcebillbid>1001A11000000017VHQ9</csourcebillbid>
          <vsourcebillcode>1BG-16111123</vsourcebillcode>
          <vsourcerowno>1001A11000000017VHPZ</vsourcerowno>
          <cprojectid>
          </cprojectid>
          <casscustid>
          </casscustid>
          <cfirsttype>55C2</cfirsttype>
          <cfirsttranstype>0001A110000000001MSJ</cfirsttranstype>
          <cfirstbillhid>1001A11000000016JXCR</cfirstbillhid>
          <vfirstbillcode>1MO-16110002</vfirstbillcode>
          <vfirstrowno>
          </vfirstrowno>
          <cfirstbillbid>1001A11000000016JXCR</cfirstbillbid>
          <vnotebody>
          </vnotebody>
          <bbarcodeclose>N</bbarcodeclose>
          <bonroadflag>N</bonroadflag>
          <dproducedate>2016/11/27 0:00:00</dproducedate>
          <pk_org>K01</pk_org>
          <pk_org_v>K01</pk_org_v>
          <cbodywarehouseid>CP002</cbodywarehouseid>
          <flargess>N</flargess>
          <pk_batchcode>
          </pk_batchcode>
          <csrcmaterialoid>
          </csrcmaterialoid>
          <csrcmaterialvid>
          </csrcmaterialvid>
          <cproductid>1202020013</cproductid>
          <fproductclass>1</fproductclass>
          <vbdef1>8076.860000</vbdef1>
        </item>
        <item>
          <cgeneralbid>
          </cgeneralbid>
          <crowno>9</crowno>
          <pk_group>001</pk_group>
          <corpoid>K01</corpoid>
          <corpvid>K01</corpvid>
          <cstateid>2</cstateid>
          <cmaterialoid>1202020013</cmaterialoid>
          <cmaterialvid>1202020013</cmaterialvid>
          <vfree1>265</vfree1>
          <vfree2>01</vfree2>
          <vfree3>01</vfree3>
          <vfree4>
          </vfree4>
          <vfree5>
          </vfree5>
          <vfree6>
          </vfree6>
          <cunitid>Pcs</cunitid>
          <castunitid>WA</castunitid>
          <vchangerate>1/265.0000</vchangerate>
          <vbatchcode>161111020717</vbatchcode>
          <nshouldnum>30</nshouldnum>
          <nshouldassistnum>7950.000</nshouldassistnum>
          <nnum>30</nnum>
          <nassistnum>7950.000</nassistnum>
          <dbizdate>2016-11-28 07:50:00</dbizdate>
          <vproductbatch>1MO-16110002</vproductbatch>
          <csourcebillhid>1001A11000000017VHPQ</csourcebillhid>
          <csourcebillbid>1001A11000000017VHQA</csourcebillbid>
          <csourcetype>55A4</csourcetype>
          <csourcetranstype>0001A110000000001MSI</csourcetranstype>
          <csourcebillbid>1001A11000000017VHQA</csourcebillbid>
          <vsourcebillcode>1BG-16111123</vsourcebillcode>
          <vsourcerowno>1001A11000000017VHQ0</vsourcerowno>
          <cprojectid>
          </cprojectid>
          <casscustid>
          </casscustid>
          <cfirsttype>55C2</cfirsttype>
          <cfirsttranstype>0001A110000000001MSJ</cfirsttranstype>
          <cfirstbillhid>1001A11000000016JXCR</cfirstbillhid>
          <vfirstbillcode>1MO-16110002</vfirstbillcode>
          <vfirstrowno>
          </vfirstrowno>
          <cfirstbillbid>1001A11000000016JXCR</cfirstbillbid>
          <vnotebody>
          </vnotebody>
          <bbarcodeclose>N</bbarcodeclose>
          <bonroadflag>N</bonroadflag>
          <dproducedate>2016/11/27 0:00:00</dproducedate>
          <pk_org>K01</pk_org>
          <pk_org_v>K01</pk_org_v>
          <cbodywarehouseid>CP002</cbodywarehouseid>
          <flargess>N</flargess>
          <pk_batchcode>
          </pk_batchcode>
          <csrcmaterialoid>
          </csrcmaterialoid>
          <csrcmaterialvid>
          </csrcmaterialvid>
          <cproductid>1202020013</cproductid>
          <fproductclass>1</fproductclass>
          <vbdef1>8075.460000</vbdef1>
        </item>
        <item>
          <cgeneralbid>
          </cgeneralbid>
          <crowno>10</crowno>
          <pk_group>001</pk_group>
          <corpoid>K01</corpoid>
          <corpvid>K01</corpvid>
          <cstateid>2</cstateid>
          <cmaterialoid>1202020013</cmaterialoid>
          <cmaterialvid>1202020013</cmaterialvid>
          <vfree1>265</vfree1>
          <vfree2>01</vfree2>
          <vfree3>01</vfree3>
          <vfree4>
          </vfree4>
          <vfree5>
          </vfree5>
          <vfree6>
          </vfree6>
          <cunitid>Pcs</cunitid>
          <castunitid>WA</castunitid>
          <vchangerate>1/265.0000</vchangerate>
          <vbatchcode>161111020720</vbatchcode>
          <nshouldnum>30</nshouldnum>
          <nshouldassistnum>7950.000</nshouldassistnum>
          <nnum>30</nnum>
          <nassistnum>7950.000</nassistnum>
          <dbizdate>2016-11-28 07:50:00</dbizdate>
          <vproductbatch>1MO-16110002</vproductbatch>
          <csourcebillhid>1001A11000000017VHPQ</csourcebillhid>
          <csourcebillbid>1001A11000000017VHQB</csourcebillbid>
          <csourcetype>55A4</csourcetype>
          <csourcetranstype>0001A110000000001MSI</csourcetranstype>
          <csourcebillbid>1001A11000000017VHQB</csourcebillbid>
          <vsourcebillcode>1BG-16111123</vsourcebillcode>
          <vsourcerowno>1001A11000000017VHQ1</vsourcerowno>
          <cprojectid>
          </cprojectid>
          <casscustid>
          </casscustid>
          <cfirsttype>55C2</cfirsttype>
          <cfirsttranstype>0001A110000000001MSJ</cfirsttranstype>
          <cfirstbillhid>1001A11000000016JXCR</cfirstbillhid>
          <vfirstbillcode>1MO-16110002</vfirstbillcode>
          <vfirstrowno>
          </vfirstrowno>
          <cfirstbillbid>1001A11000000016JXCR</cfirstbillbid>
          <vnotebody>
          </vnotebody>
          <bbarcodeclose>N</bbarcodeclose>
          <bonroadflag>N</bonroadflag>
          <dproducedate>2016/11/27 0:00:00</dproducedate>
          <pk_org>K01</pk_org>
          <pk_org_v>K01</pk_org_v>
          <cbodywarehouseid>CP002</cbodywarehouseid>
          <flargess>N</flargess>
          <pk_batchcode>
          </pk_batchcode>
          <csrcmaterialoid>
          </csrcmaterialoid>
          <csrcmaterialvid>
          </csrcmaterialvid>
          <cproductid>1202020013</cproductid>
          <fproductclass>1</fproductclass>
          <vbdef1>8076.860000</vbdef1>
        </item>
      </cgeneralbid>
      <cwarehouseid>CP002</cwarehouseid>
      <ctrantypeid>0001A110000000001MQC</ctrantypeid>
      <vtrantypecode>46-01</vtrantypecode>
      <cprocalbodyoid>K01</cprocalbodyoid>
      <cprocalbodyvid>K01</cprocalbodyvid>
      <cprowarehouseid>CP002</cprowarehouseid>
      <cwhsmanagerid>
      </cwhsmanagerid>
      <cdptid>K013C5</cdptid>
      <cdptvid>K013C5</cdptvid>
      <cbizid>
      </cbizid>
      <vnote>11.27 夜班 102A </vnote>
      <fbillflag>2</fbillflag>
      <creator>junjie.hao</creator>
      <billmaker>junjie.hao</billmaker>
      <creationtime>2016-11-28 05:41:25</creationtime>
    </billhead>
  </bill>
</ufinterface>